[
  {
    "inputs": [],
    "stateMutability": "nonpayable",
    "type": "constructor"
  },
  {
    "anonymous": false,
    "inputs": [
      {
        "indexed": false,
        "internalType": "int64[]",
        "name": "finalPrices",
        "type": "int64[]"
      },
      {
        "indexed": false,
        "internalType": "bool",
        "name": "userIsWinner",
        "type": "bool"
      }
    ],
    "name": "Resolved",
    "type": "event"
  },
  {
    "inputs": [],
    "name": "asset",
    "outputs": [
      {
        "internalType": "bytes32",
        "name": "",
        "type": "bytes32"
      }
    ],
    "stateMutability": "view",
    "type": "function"
  },
  {
    "inputs": [],
    "name": "buyinAmount",
    "outputs": [
      {
        "internalType": "uint256",
        "name": "",
        "type": "uint256"
      }
    ],
    "stateMutability": "view",
    "type": "function"
  },
  {
    "inputs": [],
    "name": "chainedMarketsAMM",
    "outputs": [
      {
        "internalType": "contract IChainedSpeedMarketsAMM",
        "name": "",
        "type": "address"
      }
    ],
    "stateMutability": "view",
    "type": "function"
  },
  {
    "inputs": [],
    "name": "createdAt",
    "outputs": [
      {
        "internalType": "uint256",
        "name": "",
        "type": "uint256"
      }
    ],
    "stateMutability": "view",
    "type": "function"
  },
  {
    "inputs": [
      {
        "internalType": "uint256",
        "name": "",
        "type": "uint256"
      }
    ],
    "name": "directions",
    "outputs": [
      {
        "internalType": "enum SpeedMarket.Direction",
        "name": "",
        "type": "uint8"
      }
    ],
    "stateMutability": "view",
    "type": "function"
  },
  {
    "inputs": [
      {
        "internalType": "uint256",
        "name": "",
        "type": "uint256"
      }
    ],
    "name": "finalPrices",
    "outputs": [
      {
        "internalType": "int64",
        "name": "",
        "type": "int64"
      }
    ],
    "stateMutability": "view",
    "type": "function"
  },
  {
    "inputs": [],
    "name": "initialStrikePrice",
    "outputs": [
      {
        "internalType": "int64",
        "name": "",
        "type": "int64"
      }
    ],
    "stateMutability": "view",
    "type": "function"
  },
  {
    "inputs": [],
    "name": "initialStrikeTime",
    "outputs": [
      {
        "internalType": "uint64",
        "name": "",
        "type": "uint64"
      }
    ],
    "stateMutability": "view",
    "type": "function"
  },
  {
    "inputs": [
      {
        "components": [
          {
            "internalType": "address",
            "name": "_chainedMarketsAMM",
            "type": "address"
          },
          {
            "internalType": "address",
            "name": "_user",
            "type": "address"
          },
          {
            "internalType": "bytes32",
            "name": "_asset",
            "type": "bytes32"
          },
          {
            "internalType": "uint64",
            "name": "_timeFrame",
            "type": "uint64"
          },
          {
            "internalType": "uint64",
            "name": "_initialStrikeTime",
            "type": "uint64"
          },
          {
            "internalType": "uint64",
            "name": "_strikeTime",
            "type": "uint64"
          },
          {
            "internalType": "int64",
            "name": "_initialStrikePrice",
            "type": "int64"
          },
          {
            "internalType": "enum SpeedMarket.Direction[]",
            "name": "_directions",
            "type": "uint8[]"
          },
          {
            "internalType": "uint256",
            "name": "_buyinAmount",
            "type": "uint256"
          },
          {
            "internalType": "uint256",
            "name": "_safeBoxImpact",
            "type": "uint256"
          },
          {
            "internalType": "uint256",
            "name": "_payoutMultiplier",
            "type": "uint256"
          }
        ],
        "internalType": "struct ChainedSpeedMarket.InitParams",
        "name": "params",
        "type": "tuple"
      }
    ],
    "name": "initialize",
    "outputs": [],
    "stateMutability": "nonpayable",
    "type": "function"
  },
  {
    "inputs": [],
    "name": "initialized",
    "outputs": [
      {
        "internalType": "bool",
        "name": "",
        "type": "bool"
      }
    ],
    "stateMutability": "view",
    "type": "function"
  },
  {
    "inputs": [],
    "name": "isUserWinner",
    "outputs": [
      {
        "internalType": "bool",
        "name": "",
        "type": "bool"
      }
    ],
    "stateMutability": "view",
    "type": "function"
  },
  {
    "inputs": [],
    "name": "numOfDirections",
    "outputs": [
      {
        "internalType": "uint256",
        "name": "",
        "type": "uint256"
      }
    ],
    "stateMutability": "view",
    "type": "function"
  },
  {
    "inputs": [],
    "name": "numOfPrices",
    "outputs": [
      {
        "internalType": "uint256",
        "name": "",
        "type": "uint256"
      }
    ],
    "stateMutability": "view",
    "type": "function"
  },
  {
    "inputs": [],
    "name": "payoutMultiplier",
    "outputs": [
      {
        "internalType": "uint256",
        "name": "",
        "type": "uint256"
      }
    ],
    "stateMutability": "view",
    "type": "function"
  },
  {
    "inputs": [
      {
        "internalType": "int64[]",
        "name": "_finalPrices",
        "type": "int64[]"
      },
      {
        "internalType": "bool",
        "name": "_isManually",
        "type": "bool"
      }
    ],
    "name": "resolve",
    "outputs": [],
    "stateMutability": "nonpayable",
    "type": "function"
  },
  {
    "inputs": [],
    "name": "resolved",
    "outputs": [
      {
        "internalType": "bool",
        "name": "",
        "type": "bool"
      }
    ],
    "stateMutability": "view",
    "type": "function"
  },
  {
    "inputs": [],
    "name": "safeBoxImpact",
    "outputs": [
      {
        "internalType": "uint256",
        "name": "",
        "type": "uint256"
      }
    ],
    "stateMutability": "view",
    "type": "function"
  },
  {
    "inputs": [
      {
        "internalType": "uint256",
        "name": "",
        "type": "uint256"
      }
    ],
    "name": "strikePrices",
    "outputs": [
      {
        "internalType": "int64",
        "name": "",
        "type": "int64"
      }
    ],
    "stateMutability": "view",
    "type": "function"
  },
  {
    "inputs": [],
    "name": "strikeTime",
    "outputs": [
      {
        "internalType": "uint64",
        "name": "",
        "type": "uint64"
      }
    ],
    "stateMutability": "view",
    "type": "function"
  },
  {
    "inputs": [],
    "name": "timeFrame",
    "outputs": [
      {
        "internalType": "uint64",
        "name": "",
        "type": "uint64"
      }
    ],
    "stateMutability": "view",
    "type": "function"
  },
  {
    "inputs": [],
    "name": "user",
    "outputs": [
      {
        "internalType": "address",
        "name": "",
        "type": "address"
      }
    ],
    "stateMutability": "view",
    "type": "function"
  }
]
