[
  {
    "anonymous": false,
    "inputs": [
      {
        "indexed": false,
        "internalType": "address",
        "name": "sender",
        "type": "address"
      },
      {
        "indexed": false,
        "internalType": "address",
        "name": "receiver",
        "type": "address"
      },
      {
        "indexed": false,
        "internalType": "bytes",
        "name": "message",
        "type": "bytes"
      }
    ],
    "name": "MessageSent",
    "type": "event"
  },
  {
    "inputs": [
      {
        "internalType": "uint64",
        "name": "destinationChainSelector",
        "type": "uint64"
      },
      {
        "components": [
          {
            "internalType": "bytes",
            "name": "receiver",
            "type": "bytes"
          },
          {
            "internalType": "bytes",
            "name": "data",
            "type": "bytes"
          },
          {
            "components": [
              {
                "internalType": "address",
                "name": "token",
                "type": "address"
              },
              {
                "internalType": "uint256",
                "name": "amount",
                "type": "uint256"
              }
            ],
            "internalType": "struct Client.EVMTokenAmount[]",
            "name": "tokenAmounts",
            "type": "tuple[]"
          },
          {
            "internalType": "address",
            "name": "feeToken",
            "type": "address"
          },
          {
            "internalType": "bytes",
            "name": "extraArgs",
            "type": "bytes"
          }
        ],
        "internalType": "struct Client.EVM2AnyMessage",
        "name": "message",
        "type": "tuple"
      }
    ],
    "name": "ccipSend",
    "outputs": [
      {
        "internalType": "bytes32",
        "name": "",
        "type": "bytes32"
      }
    ],
    "stateMutability": "payable",
    "type": "function"
  },
  {
    "inputs": [
      {
        "internalType": "uint64",
        "name": "destinationChainSelector",
        "type": "uint64"
      },
      {
        "components": [
          {
            "internalType": "bytes",
            "name": "receiver",
            "type": "bytes"
          },
          {
            "internalType": "bytes",
            "name": "data",
            "type": "bytes"
          },
          {
            "components": [
              {
                "internalType": "address",
                "name": "token",
                "type": "address"
              },
              {
                "internalType": "uint256",
                "name": "amount",
                "type": "uint256"
              }
            ],
            "internalType": "struct Client.EVMTokenAmount[]",
            "name": "tokenAmounts",
            "type": "tuple[]"
          },
          {
            "internalType": "address",
            "name": "feeToken",
            "type": "address"
          },
          {
            "internalType": "bytes",
            "name": "extraArgs",
            "type": "bytes"
          }
        ],
        "internalType": "struct Client.EVM2AnyMessage",
        "name": "message",
        "type": "tuple"
      }
    ],
    "name": "getFee",
    "outputs": [
      {
        "internalType": "uint256",
        "name": "fee",
        "type": "uint256"
      }
    ],
    "stateMutability": "view",
    "type": "function"
  },
  {
    "stateMutability": "payable",
    "type": "receive"
  }
]
