[
  {
    "anonymous": false,
    "inputs": [
      {
        "indexed": false,
        "internalType": "uint8",
        "name": "version",
        "type": "uint8"
      }
    ],
    "name": "Initialized",
    "type": "event"
  },
  {
    "anonymous": false,
    "inputs": [
      {
        "indexed": false,
        "internalType": "address",
        "name": "market",
        "type": "address"
      },
      {
        "indexed": true,
        "internalType": "bytes32",
        "name": "gameId",
        "type": "bytes32"
      },
      {
        "indexed": false,
        "internalType": "string",
        "name": "gameLabel",
        "type": "string"
      },
      {
        "indexed": false,
        "internalType": "uint256",
        "name": "maturityDate",
        "type": "uint256"
      },
      {
        "indexed": false,
        "internalType": "uint256",
        "name": "expiryDate",
        "type": "uint256"
      },
      {
        "indexed": false,
        "internalType": "uint256",
        "name": "initialMint",
        "type": "uint256"
      },
      {
        "indexed": false,
        "internalType": "uint256",
        "name": "positionCount",
        "type": "uint256"
      },
      {
        "indexed": false,
        "internalType": "uint256[]",
        "name": "tags",
        "type": "uint256[]"
      },
      {
        "indexed": false,
        "internalType": "bool",
        "name": "isChild",
        "type": "bool"
      },
      {
        "indexed": false,
        "internalType": "address",
        "name": "parent",
        "type": "address"
      }
    ],
    "name": "MarketCreated",
    "type": "event"
  },
  {
    "anonymous": false,
    "inputs": [
      {
        "indexed": false,
        "internalType": "address",
        "name": "oldOwner",
        "type": "address"
      },
      {
        "indexed": false,
        "internalType": "address",
        "name": "newOwner",
        "type": "address"
      }
    ],
    "name": "OwnerChanged",
    "type": "event"
  },
  {
    "anonymous": false,
    "inputs": [
      {
        "indexed": false,
        "internalType": "address",
        "name": "newOwner",
        "type": "address"
      }
    ],
    "name": "OwnerNominated",
    "type": "event"
  },
  {
    "anonymous": false,
    "inputs": [
      {
        "indexed": false,
        "internalType": "address",
        "name": "_limitOrderProvider",
        "type": "address"
      }
    ],
    "name": "SetLimitOrderProvider",
    "type": "event"
  },
  {
    "anonymous": false,
    "inputs": [
      {
        "indexed": false,
        "internalType": "address",
        "name": "_sportsAMM",
        "type": "address"
      }
    ],
    "name": "SetSportsAMM",
    "type": "event"
  },
  {
    "anonymous": false,
    "inputs": [
      {
        "indexed": false,
        "internalType": "address",
        "name": "_positionMastercopy",
        "type": "address"
      }
    ],
    "name": "SportPositionMastercopyChanged",
    "type": "event"
  },
  {
    "anonymous": false,
    "inputs": [
      {
        "indexed": false,
        "internalType": "address",
        "name": "_positionalMarketManager",
        "type": "address"
      }
    ],
    "name": "SportPositionalMarketManagerChanged",
    "type": "event"
  },
  {
    "anonymous": false,
    "inputs": [
      {
        "indexed": false,
        "internalType": "address",
        "name": "_positionalMarketMastercopy",
        "type": "address"
      }
    ],
    "name": "SportPositionalMarketMastercopyChanged",
    "type": "event"
  },
  {
    "inputs": [],
    "name": "acceptOwnership",
    "outputs": [],
    "stateMutability": "nonpayable",
    "type": "function"
  },
  {
    "inputs": [
      {
        "components": [
          {
            "internalType": "address",
            "name": "creator",
            "type": "address"
          },
          {
            "internalType": "contract IERC20",
            "name": "_sUSD",
            "type": "address"
          },
          {
            "internalType": "bytes32",
            "name": "gameId",
            "type": "bytes32"
          },
          {
            "internalType": "string",
            "name": "gameLabel",
            "type": "string"
          },
          {
            "internalType": "uint256[2]",
            "name": "times",
            "type": "uint256[2]"
          },
          {
            "internalType": "uint256",
            "name": "initialMint",
            "type": "uint256"
          },
          {
            "internalType": "uint256",
            "name": "positionCount",
            "type": "uint256"
          },
          {
            "internalType": "address",
            "name": "theRundownConsumer",
            "type": "address"
          },
          {
            "internalType": "uint256[]",
            "name": "tags",
            "type": "uint256[]"
          },
          {
            "internalType": "bool",
            "name": "isChild",
            "type": "bool"
          },
          {
            "internalType": "address",
            "name": "parentMarket",
            "type": "address"
          },
          {
            "internalType": "bool",
            "name": "isDoubleChance",
            "type": "bool"
          }
        ],
        "internalType": "struct SportPositionalMarketFactory.SportPositionCreationMarketParameters",
        "name": "_parameters",
        "type": "tuple"
      }
    ],
    "name": "createMarket",
    "outputs": [
      {
        "internalType": "contract SportPositionalMarket",
        "name": "",
        "type": "address"
      }
    ],
    "stateMutability": "nonpayable",
    "type": "function"
  },
  {
    "inputs": [
      {
        "internalType": "address",
        "name": "_owner",
        "type": "address"
      }
    ],
    "name": "initialize",
    "outputs": [],
    "stateMutability": "nonpayable",
    "type": "function"
  },
  {
    "inputs": [
      {
        "internalType": "address",
        "name": "_owner",
        "type": "address"
      }
    ],
    "name": "nominateNewOwner",
    "outputs": [],
    "stateMutability": "nonpayable",
    "type": "function"
  },
  {
    "inputs": [],
    "name": "nominatedOwner",
    "outputs": [
      {
        "internalType": "address",
        "name": "",
        "type": "address"
      }
    ],
    "stateMutability": "view",
    "type": "function"
  },
  {
    "inputs": [],
    "name": "owner",
    "outputs": [
      {
        "internalType": "address",
        "name": "",
        "type": "address"
      }
    ],
    "stateMutability": "view",
    "type": "function"
  },
  {
    "inputs": [],
    "name": "positionMastercopy",
    "outputs": [
      {
        "internalType": "address",
        "name": "",
        "type": "address"
      }
    ],
    "stateMutability": "view",
    "type": "function"
  },
  {
    "inputs": [],
    "name": "positionalMarketManager",
    "outputs": [
      {
        "internalType": "address",
        "name": "",
        "type": "address"
      }
    ],
    "stateMutability": "view",
    "type": "function"
  },
  {
    "inputs": [],
    "name": "positionalMarketMastercopy",
    "outputs": [
      {
        "internalType": "address",
        "name": "",
        "type": "address"
      }
    ],
    "stateMutability": "view",
    "type": "function"
  },
  {
    "inputs": [
      {
        "internalType": "address",
        "name": "_owner",
        "type": "address"
      }
    ],
    "name": "setOwner",
    "outputs": [],
    "stateMutability": "nonpayable",
    "type": "function"
  },
  {
    "inputs": [
      {
        "internalType": "address",
        "name": "_positionMastercopy",
        "type": "address"
      }
    ],
    "name": "setSportPositionMastercopy",
    "outputs": [],
    "stateMutability": "nonpayable",
    "type": "function"
  },
  {
    "inputs": [
      {
        "internalType": "address",
        "name": "_positionalMarketManager",
        "type": "address"
      }
    ],
    "name": "setSportPositionalMarketManager",
    "outputs": [],
    "stateMutability": "nonpayable",
    "type": "function"
  },
  {
    "inputs": [
      {
        "internalType": "address",
        "name": "_positionalMarketMastercopy",
        "type": "address"
      }
    ],
    "name": "setSportPositionalMarketMastercopy",
    "outputs": [],
    "stateMutability": "nonpayable",
    "type": "function"
  },
  {
    "inputs": [
      {
        "internalType": "address",
        "name": "_sportsAMM",
        "type": "address"
      }
    ],
    "name": "setSportsAMM",
    "outputs": [],
    "stateMutability": "nonpayable",
    "type": "function"
  },
  {
    "inputs": [],
    "name": "sportsAMM",
    "outputs": [
      {
        "internalType": "address",
        "name": "",
        "type": "address"
      }
    ],
    "stateMutability": "view",
    "type": "function"
  },
  {
    "inputs": [
      {
        "internalType": "address",
        "name": "proxyAddress",
        "type": "address"
      }
    ],
    "name": "transferOwnershipAtInit",
    "outputs": [],
    "stateMutability": "nonpayable",
    "type": "function"
  }
]
